.coveragerc
.gitignore
.isort.cfg
.pre-commit-config.yaml
.readthedocs.yml
AUTHORS.md
CHANGELOG.md
LICENSE.txt
README.md
pyproject.toml
setup.cfg
setup.py
tox.ini
docs/Makefile
docs/authors.md
docs/changelog.md
docs/conf.py
docs/index.md
docs/license.rst
docs/readme.md
docs/requirements.txt
docs/_static/.gitignore
examples/.gitignore
examples/COG-EarthData.ipynb
examples/NonCOG-NASA-CMR.ipynb
src/eo_learn_stac.egg-info/PKG-INFO
src/eo_learn_stac.egg-info/SOURCES.txt
src/eo_learn_stac.egg-info/dependency_links.txt
src/eo_learn_stac.egg-info/not-zip-safe
src/eo_learn_stac.egg-info/requires.txt
src/eo_learn_stac.egg-info/top_level.txt
src/eolearn/__init__.py
src/eolearn/stac/__init__.py
src/eolearn/stac/stac.py
src/eolearn/stac/tasks.py
src/eolearn/stac/utils.py
tests/conftest.py
tests/test_skeleton.py