Metadata-Version: 2.1
Name: eo-learn-stac
Version: 0.1.1
Summary: eo-learn tasks for consuming SpatioTemporal Asset Catalogs (STAC)
Home-page: https://github.com/dymaxionlabs/eo-learn-stac/
Author: Damián Silvani
Author-email: munshkr@gmail.com
License: MIT
Project-URL: Documentation, https://eo-learn-stac.readthedocs.io/en/latest/
Project-URL: Source, https://github.com/dymaxionlabs/eo-learn-stac/
Project-URL: Changelog, https://eo-learn-stac.readthedocs.io/en/latest/changelog.html
Project-URL: Tracker, https://github.com/dymaxionlabs/eo-learn-stac/issues
Platform: any
Classifier: Development Status :: 4 - Beta
Classifier: Programming Language :: Python
Provides-Extra: testing
License-File: LICENSE.txt
License-File: AUTHORS.md
